speaksee/__init__.py
speaksee/utils.py
speaksee/vocab.py
speaksee/data/__init__.py
speaksee/data/dataset.py
speaksee/data/example.py
speaksee/data/field.py
speaksee/data/pipeline.py
speaksee/data/utils.py
speaksee/evaluation/__init__.py
speaksee/evaluation/stanford-corenlp-3.4.1.jar
speaksee/evaluation/tokenizer.py
speaksee/evaluation/bleu/__init__.py
speaksee/evaluation/bleu/bleu.py
speaksee/evaluation/bleu/bleu_scorer.py
speaksee/evaluation/cider/__init__.py
speaksee/evaluation/cider/cider.py
speaksee/evaluation/cider/cider_scorer.py
speaksee/evaluation/meteor/__init__.py
speaksee/evaluation/meteor/meteor.py
speaksee/evaluation/recall/__init__.py
speaksee/evaluation/recall/recall.py
speaksee/evaluation/rouge/__init__.py
speaksee/evaluation/rouge/rouge.py
speaksee/evaluation/spice/__init__.py
speaksee/evaluation/spice/spice.py
speaksee/models/CaptioningModel.py
speaksee/models/VSbaseline.py
speaksee/models/VisualSemanticModel.py
speaksee/models/__init__.py
speaksee/models/bottomup_topdown_attention.py
speaksee/models/fc.py
speaksee/models/scan.py
speaksee-0.0.1.dist-info/LICENSE
speaksee-0.0.1.dist-info/METADATA
speaksee-0.0.1.dist-info/WHEEL
speaksee-0.0.1.dist-info/top_level.txt
speaksee-0.0.1.dist-info/RECORD
